{
  "ledger": {
    "blockchain": "BLOCKCHAIN_ETHEREUM",
    "network": "NETWORK_ETHEREUM_MAINNET",
    "identifier": {
      "hsh": "0x38d41d2096a98d2e1afe42b0cb1eaad33dce00916cbd3443dcb05016f362fb45",
      "index": "49773"
    },
    "previousLedger": {
      "hsh": "0x3ff02ccf94c1b0b20fe03862e19024db4d1bfa4c9dce3d13035d4893b88c78a7",
      "index": "49772"
    },
    "timestamp": "2023-02-08T16:37:24Z",
    "ethereumMetadata": {
      "baseFee": {
        "amount": "7",
        "currency": "ETH",
        "amountString": "7",
        "currencyIdentifier": {
          "id": "native/ETH",
          "symbol": "ETH"
        }
      },
      "blockCreatorFee": {
        "amount": "0",
        "currency": "ETH",
        "amountString": "0",
        "currencyIdentifier": {
          "id": "native/ETH",
          "symbol": "ETH"
        }
      },
      "feeRecipient": "0xf97e180c050e5ab072211ad2c213eb5aee4df134"
    }
  },
  "transactions": [
    {
      "blockchain": "BLOCKCHAIN_ETHEREUM",
      "network": "NETWORK_ETHEREUM_MAINNET",
      "identifier": {
        "hsh": "0x75dc553fe0787f7aee93ea0e89062164d650574cc3ec871d1c7966de225f5867"
      },
      "ledger": {
        "hsh": "0x38d41d2096a98d2e1afe42b0cb1eaad33dce00916cbd3443dcb05016f362fb45",
        "index": "49773"
      },
      "fee": {
        "amountString": "0"
      },
      "operations": [
        {
          "blockchain": "BLOCKCHAIN_ETHEREUM",
          "network": "NETWORK_ETHEREUM_MAINNET",
          "type": "OUTPUT",
          "to": {
            "address": "0xf97e180c050e5ab072211ad2c213eb5aee4df134"
          },
          "amount": {
            "amount": "191408000000000",
            "currency": "ETH",
            "amountString": "191408000000000",
            "currencyIdentifier": {
              "id": "native/ETH",
              "symbol": "ETH"
            }
          },
          "ethereumMetadata": {
            "withdrawal_validator_index": "0xc2d0"
          }
        }
      ],
      "ethereumMetadata": {},
      "status": "SUCCESS"
    },
    {
      "blockchain": "BLOCKCHAIN_ETHEREUM",
      "network": "NETWORK_ETHEREUM_MAINNET",
      "identifier": {
        "hsh": "0xfd1667da2c3f2ca7626605bd588389d3bb4c6a07c9249b4402c30abe55bf61de",
        "index": "1"
      },
      "ledger": {
        "hsh": "0x38d41d2096a98d2e1afe42b0cb1eaad33dce00916cbd3443dcb05016f362fb45",
        "index": "49773"
      },
      "fee": {
        "amountString": "0"
      },
      "operations": [
        {
          "blockchain": "BLOCKCHAIN_ETHEREUM",
          "network": "NETWORK_ETHEREUM_MAINNET",
          "type": "OUTPUT",
          "to": {
            "address": "0xf97e180c050e5ab072211ad2c213eb5aee4df134"
          },
          "amount": {
            "amount": "191408000000000",
            "currency": "ETH",
            "amountString": "191408000000000",
            "currencyIdentifier": {
              "id": "native/ETH",
              "symbol": "ETH"
            }
          },
          "ethereumMetadata": {
            "withdrawal_validator_index": "0xc2d1"
          }
        }
      ],
      "ethereumMetadata": {},
      "status": "SUCCESS"
    },
    {
      "blockchain": "BLOCKCHAIN_ETHEREUM",
      "network": "NETWORK_ETHEREUM_MAINNET",
      "identifier": {
        "hsh": "0x2e77ad87d0644dfe2488c356d6f74b7bb443a383d04e271d862d6baccfb350d1",
        "index": "2"
      },
      "ledger": {
        "hsh": "0x38d41d2096a98d2e1afe42b0cb1eaad33dce00916cbd3443dcb05016f362fb45",
        "index": "49773"
      },
      "fee": {
        "amountString": "0"
      },
      "operations": [
        {
          "blockchain": "BLOCKCHAIN_ETHEREUM",
          "network": "NETWORK_ETHEREUM_MAINNET",
          "type": "OUTPUT",
          "to": {
            "address": "0xf97e180c050e5ab072211ad2c213eb5aee4df134"
          },
          "amount": {
            "amount": "191408000000000",
            "currency": "ETH",
            "amountString": "191408000000000",
            "currencyIdentifier": {
              "id": "native/ETH",
              "symbol": "ETH"
            }
          },
          "ethereumMetadata": {
            "withdrawal_validator_index": "0xc2d2"
          }
        }
      ],
      "ethereumMetadata": {},
      "status": "SUCCESS"
    },
    {
      "blockchain": "BLOCKCHAIN_ETHEREUM",
      "network": "NETWORK_ETHEREUM_MAINNET",
      "identifier": {
        "hsh": "0x38d41d2096a98d2e1afe42b0cb1eaad33dce00916cbd3443dcb05016f362fb45",
        "index": "3"
      },
      "ledger": {
        "hsh": "0x38d41d2096a98d2e1afe42b0cb1eaad33dce00916cbd3443dcb05016f362fb45",
        "index": "49773"
      },
      "fee": {
        "amountString": "0"
      },
      "operations": [
        {
          "blockchain": "BLOCKCHAIN_ETHEREUM",
          "network": "NETWORK_ETHEREUM_MAINNET",
          "type": "BLOCK_REWARD",
          "to": {
            "address": "0xf97e180c050e5ab072211ad2c213eb5aee4df134"
          },
          "amount": {
            "amount": "0",
            "currency": "ETH",
            "amountString": "0",
            "currencyIdentifier": {
              "id": "native/ETH",
              "symbol": "ETH"
            }
          },
          "ethereumMetadata": {
            "block_creator_fee": {
              "currency": "ETH",
              "amountString": "0",
              "currencyIdentifier": {
                "id": "native/ETH",
                "symbol": "ETH"
              }
            }
          }
        }
      ],
      "ethereumMetadata": {
        "type": 2
      },
      "status": "SUCCESS"
    }
  ]
}
